{
    "utcOffset": -18000000,
    "data": [{
            "run": 0,
            "walk": 46,
            "total": 46,
            "active": 601000,
            "date": "2018-08-30T00:00:00"
        },
        {
            "run": 20,
            "walk": 10,
            "total": 0,
            "active": 0,
            "date": "2018-08-30T01:00:00"
        },
        {
            "run": 0,
            "walk": 0,
            "total": 0,
            "active": 0,
            "date": "2018-08-30T02:00:00"
        },
        {
            "run": 0,
            "walk": 0,
            "total": 0,
            "active": 0,
            "date": "2018-08-30T03:00:00"
        },
        {
            "run": 0,
            "walk": 0,
            "total": 0,
            "active": 0,
            "date": "2018-08-30T04:00:00"
        },
        {
            "run": 0,
            "walk": 0,
            "total": 0,
            "active": 0,
            "date": "2018-08-30T05:00:00"
        },
        {
            "run": 200,
            "walk": 200,
            "total": 0,
            "active": 0,
            "date": "2018-08-30T06:00:00"
        },
        {
            "run": 297,
            "walk": 201,
            "total": 498,
            "active": 1897000,
            "date": "2018-08-30T07:00:00"
        },
        {
            "run": 0,
            "walk": 0,
            "total": 0,
            "active": 0,
            "date": "2018-08-30T08:00:00"
        },
        {
            "run": 0,
            "walk": 0,
            "total": 0,
            "active": 0,
            "date": "2018-08-30T09:00:00"
        },
        {
            "run": 0,
            "walk": 0,
            "total": 0,
            "active": 0,
            "date": "2018-08-30T10:00:00"
        },
        {
            "run": 0,
            "walk": 234,
            "total": 234,
            "active": 1091000,
            "date": "2018-08-30T11:00:00"
        },
        {
            "run": 0,
            "walk": 44,
            "total": 44,
            "active": 211000,
            "date": "2018-08-30T12:00:00"
        },
        {
            "run": 0,
            "walk": 0,
            "total": 0,
            "active": 0,
            "date": "2018-08-30T13:00:00"
        },
        {
            "run": 0,
            "walk": 0,
            "total": 0,
            "active": 0,
            "date": "2018-08-30T14:00:00"
        },
        {
            "run": 0,
            "walk": 48,
            "total": 48,
            "active": 423000,
            "date": "2018-08-30T15:00:00"
        },
        {
            "run": 0,
            "walk": 90,
            "total": 90,
            "active": 470000,
            "date": "2018-08-30T16:00:00"
        },
        {
            "run": 0,
            "walk": 185,
            "total": 185,
            "active": 220000,
            "date": "2018-08-30T17:00:00"
        },
        {
            "run": 0,
            "walk": 424,
            "total": 424,
            "active": 844000,
            "date": "2018-08-30T18:00:00"
        },
        {
            "run": 0,
            "walk": 77,
            "total": 77,
            "active": 174000,
            "date": "2018-08-30T19:00:00"
        },
        {
            "run": 0,
            "walk": 0,
            "total": 0,
            "active": 0,
            "date": "2018-08-30T20:00:00"
        },
        {
            "run": 0,
            "walk": 0,
            "total": 0,
            "active": 0,
            "date": "2018-08-30T21:00:00"
        },
        {
            "run": 0,
            "walk": 0,
            "total": 0,
            "active": 0,
            "date": "2018-08-30T22:00:00"
        },
        {
            "run": 0,
            "walk": 0,
            "total": 0,
            "active": 0,
            "date": "2018-08-30T23:00:00"
        }
    ]
}